daf/__init__.py
daf/actions.py
daf/admin.py
daf/apps.py
daf/contrib.py
daf/interfaces.py
daf/migrations/0001_initial.py
daf/migrations/__init__.py
daf/models.py
daf/permissions.py
daf/registry.py
daf/rest_framework.py
daf/templates/daf/admin/_action_breadcrumbs.html
daf/templates/daf/admin/_action_buttons.html
daf/templates/daf/admin/_form_repo.js
daf/templates/daf/admin/action.html
daf/templates/daf/admin/change_form.html
daf/templates/daf/admin/change_list.html
daf/tests/__init__.py
daf/tests/actions/__init__.py
daf/tests/actions/atomic.py
daf/tests/actions/basic.py
daf/tests/actions/bulk_grant_staff_access.py
daf/tests/actions/grant_staff_access.py
daf/tests/actions/update_my_field.py
daf/tests/actions/update_my_model.py
daf/tests/admin.py
daf/tests/migrations/0001_initial.py
daf/tests/migrations/0002_mymodel_my_extra_field.py
daf/tests/migrations/__init__.py
daf/tests/models.py
daf/tests/templates/tests/action.html
daf/tests/test_actions.py
daf/tests/test_integration.py
daf/tests/test_permissions.py
daf/tests/test_registry.py
daf/tests/test_rest_framework.py
daf/tests/test_views.py
daf/tests/urls.py
daf/tests/viewsets.py
daf/urls.py
daf/utils.py
daf/views.py
django_action_framework-1.5.0.dist-info/LICENSE
django_action_framework-1.5.0.dist-info/WHEEL
django_action_framework-1.5.0.dist-info/METADATA
django_action_framework-1.5.0.dist-info/RECORD
