Metadata-Version: 2.1
Name: django-action-framework
Version: 1.5.0
Summary: Easily create actions and various interfaces around them.
Home-page: https://github.com/jyveapp/django-action-framework
License: BSD-3-Clause
Author: Wes Kendall
Requires-Python: >=3.6,<4
Classifier: Framework :: Django
Classifier: Intended Audience :: Developers
Classifier: License :: OSI Approved :: BSD License
Classifier: Operating System :: OS Independent
Classifier: Programming Language :: Python
Classifier: Programming Language :: Python :: 3
Classifier: Programming Language :: Python :: 3 :: Only
Classifier: Programming Language :: Python :: 3.6
Classifier: Programming Language :: Python :: 3.7
Classifier: Programming Language :: Python :: 3.8
Classifier: Programming Language :: Python :: 3.9
Requires-Dist: django (>=2)
Requires-Dist: django-args (>=1.4.0,<2.0.0)
Requires-Dist: djangorestframework (>=3.0.0,<4.0.0)
Requires-Dist: python-args (>=1.0.2,<2.0.0)
Project-URL: Documentation, https://django-action-framework.readthedocs.io
Project-URL: Repository, https://github.com/jyveapp/django-action-framework
